py-trade-signal/__init__.py
py-trade-signal/macd.py
py_trade_signal/__init__.py
py_trade_signal/exception.py
py_trade_signal/macd.py
py_trade_signal/mfi.py
py_trade_signal/psar.py
py_trade_signal/vzo.py
py_trade_signal-1.0.3.dist-info/LICENSE
py_trade_signal-1.0.3.dist-info/METADATA
py_trade_signal-1.0.3.dist-info/WHEEL
py_trade_signal-1.0.3.dist-info/top_level.txt
py_trade_signal-1.0.3.dist-info/RECORD
