Metadata-Version: 2.1
Name: py-trade-signal
Version: 1.0.3
Summary: A collection of trade signals calculated via traditional technical and fundamental analysis, with the inclusion of sentiment based indicators.
Home-page: https://github.com/bbeale/py-trade-signal
Author: bbeale
Author-email: beale.ben@gmail.com
License: Copyright (c) 2019 bbeale
